bnclassify/__init__.py
bnclassify/bnclassify.py
bnclassify/examples.py
bnclassify-1.0.1.dist-info/LICENSE
bnclassify-1.0.1.dist-info/METADATA
bnclassify-1.0.1.dist-info/WHEEL
bnclassify-1.0.1.dist-info/top_level.txt
bnclassify-1.0.1.dist-info/RECORD
