Metadata-Version: 2.1
Name: bnclassify
Version: 1.0.1
Summary: Python package for learning the graphical structure of Bayesian networks, parameter learning, inference and sampling methods.
Home-page: https://erdogant.github.io/bnlearn
Download-URL: https://github.com/erdogant/bnclassify/archive/1.0.1.tar.gz
Author: Erdogan Taskesen
Author-email: erdogant@gmail.com
License: UNKNOWN
Platform: UNKNOWN
Classifier: Programming Language :: Python :: 3
Classifier: License :: OSI Approved :: MIT License
Classifier: Operating System :: OS Independent
Requires-Python: >=3
License-File: LICENSE
Requires-Dist: bnlearn
